okapi/__init__.py
okapi/runners.py
okapi/core/__init__.py
okapi/core/exceptions.py
okapi/core/request.py
okapi/core/summary.py
okapi/core/tests.py
okapi/core/utils.py
okapi/core/loggers/__init__.py
okapi/core/loggers/base.py
okapi/core/loggers/console.py
okapi/core/loggers/tests.py
okapi/rst/__init__.py
okapi/rst/nodes.py
okapi/rst/directives/__init__.py
okapi/rst/directives/headers.py
okapi/rst/directives/request.py
okapi/rst/writers/__init__.py
okapi/rst/writers/html.py
okapi/settings/__init__.py
okapi/settings/cache.py
okapi/settings/configparser.py
okapi/settings/headers.py
okapi/settings/internal.py
okapi/settings/template.py
okapi/static/css/base.css
okapi/static/js/main.js
okapi/templates/base.html
okapi/templates/headers.html
okapi/templates/request.html
okapi/templates/exports/curl.html
okapi/templates/exports/jira.html
okapi/templatetags/__init__.py
okapi/templatetags/headers.py
okapi/templatetags/misc.py
okapi/templatetags/exports/__init__.py
okapi/templatetags/exports/base.py
okapi/templatetags/exports/curl.py
okapi/templatetags/exports/jira.py
okapi/tests/__init__.py
okapi/tests/test_runner.py
okapi/tests/utils.py
tz_okapi-0.2.10.data/scripts/okapi
tz_okapi-0.2.10.dist-info/DESCRIPTION.rst
tz_okapi-0.2.10.dist-info/METADATA
tz_okapi-0.2.10.dist-info/metadata.json
tz_okapi-0.2.10.dist-info/RECORD
tz_okapi-0.2.10.dist-info/top_level.txt
tz_okapi-0.2.10.dist-info/WHEEL
