Metadata-Version: 2.0
Name: tz-okapi
Version: 0.2.10
Summary: Okapi is a simple tool to create documentation for your API and cover
Requires-Dist: colorama (>=0.3.3)
Requires-Dist: docopt (>=0.6.1)
Requires-Dist: docutils (>=0.12)
Requires-Dist: Jinja2 (>=2.7.3)
Requires-Dist: Pygments (>=2.0.2)
Requires-Dist: requests (>=2.7.0)
Requires-Dist: urllib3 (>=1.10.4)
